moover/__init__.py
moover/__main__.py
moover/extensions.py
moover-1.1.3.dist-info/LICENSE
moover-1.1.3.dist-info/METADATA
moover-1.1.3.dist-info/WHEEL
moover-1.1.3.dist-info/entry_points.txt
moover-1.1.3.dist-info/top_level.txt
moover-1.1.3.dist-info/RECORD
