Metadata-Version: 2.1
Name: moover
Version: 1.1.3
Summary: Automagically Move Files
Home-page: https://github.com/ssiyad/automagic-file-mover
Author: Sabu Siyad
Author-email: sabu.siyad.p@gmail.com
License: MIT
Platform: UNKNOWN
Requires-Dist: py-notifier (==0.1.0)
Requires-Dist: watchdog (==0.9.0)
